Workbook

Sheet Титульный лист
B1: ООО «Архитектурно-строительное управление №7» Юр.адрес: 420059, РТ, г.Казань, ул.Оренбургский тракт, д.8Д, пом.№ 1016 ИНН: 1684002816, КПП: 168401001 Р/счет: 40702810600020016073, в ПАО «АК БАРС» БАНК К/счет: 30101810000000000805, БИК: 49205805 Тел.: +7 905 022 23 55, Email: asu-722@mail.ru
A2: РАСЧЕТНО-КАЛЬКУЛЯЦИОННАЯ ВЕДОМОСТЬ (РКМ)
A3: Наименование изделия: | B3: =Вводные_данные!$B$5
A4: Материал: | B4: =Вводные_данные!$B$11
A5: Размеры, мм: | B5: =TEXT(Вводные_данные!$B$7,"0")&" × "&TEXT(Вводные_данные!$B$8,"0")&" × "&TEXT(Вводные_данные!$B$9,"0")
A6: Количество: | B6: =TEXT(Вводные_данные!$B$6,"0")&" шт."
A7: Фактура поверхности | B7: =Вводные_данные!$B$12
A8: Основание расчета: | B8: Техническое задание на разработку ТК и РКМ (2025 г.).
A10: Составил: | B10: ________________ / ____________________
A11: Проверил (ОТК/нормоконтроль): | B11: ________________ / ____________________
A12: Утвердил: | B12: ________________ / ____________________
A14: Дата: | B14: =TEXT(TODAY(),"dd.mm.yyyy")

Sheet Инструкция_серия
A1: ИНСТРУКЦИЯ ДЛЯ СЕРИЙНОГО ВЫПУСКА РКМ ПО ЭТАЛОНУ
A3: Эталон: данный файл-шаблон. Для каждой позиции из плана создавайте отдельную копию и заполняйте вводные и разделы.
A5: Шаг | B5: Действие | C5: Где в файле
A6: 1 | B6: Сохраните копию шаблона под имя файла с номером позиции (пример: RKM_Pos_001_<короткое_имя>.xlsx). | C6: Файл
A7: 2 | B7: Заполните параметры изделия: наименование, количество, L×W×T, материал и фактуру (для титула и расчетов). | C7: Вводные_данные!B5:B12
A8: 3 | B8: Зафиксируйте методику удельных и базу (единообразно для всей серии): выберите методики в выпадающих списках и при необходимости переопределите базы м²/м.п. | C8: Вводные_данные!B23:B24 и E23/H23
A9: 4 | B9: Проверьте геометрию и потребность сырья (коэффициенты и цена блока — во вводных данных). | C9: Геометрия
A10: 5 | B10: Заполните раздел 1 (материалы/упаковка): количество, цена, реквизиты подтверждающего документа и норматив/основание (при необходимости можно заполнить позже). | C10: Материалы (колонки G–H)
A11: 6 | B11: Заполните раздел 3 (операции): нормы времени, роли/ставки, машинное время, норматив/основание и комментарии (по каждой операции). | C11: Операции
A12: 7 | B12: Заполните раздел 2 (логистика): расстояние/тариф/рейсы, погрузка/разгрузка, страхование; укажите источник/документ. | C12: Транспорт
A13: 8 | B13: Проверьте накладные/резерв/прибыль (проценты заданы во вводных данных; база начисления раскрыта формулами). | C13: Накладные_и_прибыль + Вводные_данные!E27:E29
A14: 9 | B14: Контроль результата: ИТОГО по партии, за 1 шт, за 1 м² и за 1 м.п. (с/без НДС). | C14: ИТОГО
A15: 10 | B15: Заполните подписи и дату на титульном листе; перед печатью проверьте области печати и масштаб. | C15: Титульный лист
A18: Важно: | B18: После старта серии не меняйте методику м²/м.п. и базу распределения. Если методика меняется по требованию заказчика — обновите ее единообразно во всех РКМ серии.

Sheet Вводные_данные
A1: ВВОДНЫЕ ДАННЫЕ И ДОПУЩЕНИЯ
A2: Все значения в желтых ячейках — редактируемые (исходные параметры / ставки).
A4: 1) Параметры изделия | D4: 2) Материал, коэффициенты потерь и допуски
A5: Наименование | B5: Изделие индивидуальное, архитектурное 1-й категории, калиброванное с подбором по оттенку и зернистости с минимальным содержанием жил и микротрещин элемент высокоточного индивидуального изготовления из натурального камня: угловые полукруглые балясины для внутренней отделки лестниц, сложной конфигурации по профилю (фигурный контур с профилированной базой (плинтом), вазаобразным стволом с двухрадиусным рельефным декором в средней части, основанием под декоративным элементом и резной капителью), с механизированной обработкой кромок (калибровка основания и верха) и ручной художественной доработкой поверхностей; Материал — мрамор Delikato light; Обработка - лощение, габаритные размеры 205х205хH590мм | D5: Плотность гранита, кг/м3 | E5: 2700
A6: Количество, шт | B6: 4 | D6: Коэф. припусков/керфа (объем), k_allow | E6: 1.2
A7: Длина L, мм | B7: 205 | D7: Коэф. отбора/брака (подбор партии, длина>5м), k_reject | E7: 1.4
A8: Ширина W, мм | B8: 205 | D8: Тех. запас на партию, k_reserve | E8: 1.05
A9: Толщина T, мм | B9: 590 | D9: Цена гранитного блока, руб/м3 (КП/счет) | E9: 642000
A10: Подрезка по месту (0=нет, 1=да) | B10: 1
A11: Материал (текст для титула) | B11: Мрамор месторождения "Delikato light"
A12: Фактура/отделка (текст для титула) | B12: Лощение
A13: 3) Тарифы труда (2025), руб/ч (редактируемые) | D13: 4) Тарифы машинного времени и энергоносителей
A14: Категория/роль | B14: Ставка, руб/ч | D14: Оборудование/ресурс | E14: Ставка, руб/маш-ч | F14: Примечание | G14: Средн. мощность, кВт
A15: Директор производства | B15: 609.76 | D15: SQC2200 (мостовая пила, алмаз) | E15: 6500 | F15: распиловка, учет износа дисков | G15: 25
A16: Мастер цеха (гранит/мрамор) | B16: 243.9 | D16: JC-1010 (калибровальный станок) | E16: 7000 | F16: калибровка плоскостей, толщина 150 мм | G16: 30
A17: Наладчик станков с ЧПУ | B17: 243.9 | D17: Фрезерный ЧПУ/портал | E17: 8500 | F17: контур/карман/капельник | G17: 35
A18: Распиловщик камня (Камнерез) | B18: 176.83 | D18: SQC600-4D (профильный/кромкообрабатывающий) | E18: 7200 | F18: профиль R25 на длине 5,15 м | G18: 20
A19: Электрик | B19: 176.83 | D19: Бучардировочная станция (пневмо) | E19: 4500 | F19: поверхность 1 кат. | G19: 10
A20: Разнорабочий | B20: 152.44 | D20: ZLMS 2600 / SPG1200-12 (лощильная линия) | E20: 6000 | F20: лицевые плоскости | G20: 15
A21: Инженер КИПиА | B21: 176.83 | D21: Кран-балка (внутрицех.) | E21: 2000 | F21: перемещения/перевороты | G21: 5
A22: 5) База удельных расчетов (м²/м.п.) | D22: 6) Методика удельных (справочно)
A23: База м² на 1 шт., м² | B23: =Геометрия!$B$22 | C23: По умолчанию: =Геометрия!B22. Можно заменить вручную (единая база для серии). | D23: Методика м² | E23: верхняя плоскость (L×W) | F23: Зафиксируйте для всей серии. | G23: Методика м.п. | H23: по длине L | I23: Зафиксируйте для всей серии.
A24: База м.п. на 1 шт., м | B24: =Геометрия!$B$23 | C24: По умолчанию: =Геометрия!B23. Можно заменить вручную (единая база для серии). | D24: Электроэнергия, руб/кВт·ч | E24: 12
D25: Коэф. страховых взносов на ФОТ (пример) | E25: 0.302
D26: НДС (ставка 2025), доля | E26: 0.2
D27: Накладные расходы (от ФОТ рабочих), доля | E27: 1.73
D28: Прибыль (от себестоимости), доля | E28: 0.34
D29: Резерв на технологические риски/брак, доля | E29: 0.08 | F29: коэф. на риск длины>5 м, профиль R25, двойная отделка

Sheet Геометрия
A1: ГЕОМЕТРИЯ, ОБЪЕМЫ И ПЛОЩАДИ
A2: ="Расчет выполнен по габаритам изделия "&TEXT(Вводные_данные!$B$7,"0")&"×"&TEXT(Вводные_данные!$B$8,"0")&"×"&TEXT(Вводные_данные!$B$9,"0")&" мм; длина допускает подрезку по месту (учтено коэффициентом k_reserve)."
A4: Параметр | B4: Значение | C4: Формула/источник | E4: Расчет потребности в сырье (гранитный блок)
A5: Длина L, м | B5: =Вводные_данные!$B$7/1000 | C5: из ТЗ | E5: Коэф. Припусков | F5: =Вводные_данные!$E$6
A6: Ширина W, м | B6: =Вводные_данные!$B$8/1000 | C6: из ТЗ | E6: Коэф. отбора/брака | F6: =Вводные_данные!$E$7
A7: Толщина T, м | B7: =Вводные_данные!$B$9/1000 | C7: из ТЗ | E7: Тех. Запас | F7: =Вводные_данные!$E$8
A8: Объем чистый V_net, м³ (1 шт) | B8: =B5*B6*B7 | C8: L×W×T | E8: Потребность объема сырья, м³ (на партию) | F8: =B19*F5*F6*F7
A9: Площадь верхней плоскости, м² | B9: =B5*B6 | C9: L×W | E9: Потребность объема сырья, м³ (на 1 шт) | F9: =B8*F5*F6*F7
A10: Площадь нижней плоскости, м² | B10: =B5*B6 | C10: L×W | E10: Стоимость сырья, руб (на партию) | F10: =F8*Вводные_данные!$E$9
A11: Площадь лицевой (передней) грани, м² | B11: =B5*B7 | C11: L×T | E11: Стоимость сырья, руб (на 1 шт) | F11: =F9*Вводные_данные!$E$9
A12: Площадь тыльной грани, м² | B12: =B5*B7 | C12: L×T
A13: Площадь торцов (2 шт), м² | B13: =2*B6*B7 | C13: 2×W×T
A14: Полная площадь всех граней, м² | B14: =2*(B9+B11)+B13 | C14: сумма
A15: Длина профиля R25 (фронт + торцы), пог.м | B15: =B5+2*B6 | C15: L + 2×W
A16: Периметр для калибровки/кромок (все ребра), пог.м | B16: =4*B5+4*B6 | C16: 12 ребер
A17: Масса 1 шт, кг | B17: =B8*Вводные_данные!$E$5 | C17: V_net×плотность
A18: Количество, шт | B18: =Вводные_данные!$B$6
A19: Объем чистый на партию, м³ | B19: =B8*B18 | C19: V_net×кол-во
A20: Масса партии, кг | B20: =B17*B18 | C20: масса×кол-во
A22: Площадь для удельной стоимости, м² (на 1 шт) | B22: =B9 | C22: по умолчанию: верхняя плоскость (B9). Можно заменить, напр., на B14.
A23: Длина для удельной стоимости, м.п. (на 1 шт) | B23: =B5 | C23: по умолчанию: длина L (B5). Можно заменить, напр., на B15 или B16.

Sheet Материалы
A1: РАЗДЕЛ 1 — МАТЕРИАЛЫ, ИНСТРУМЕНТ, УПАКОВКА
A2: Требование: каждая статья имеет формулу количества и реквизит подтверждающего документа (может быть заполнен позже).
A4: № | B4: Наименование (полное) | C4: Ед. | D4: Кол-во (партия) | E4: Цена, руб/ед | F4: Сумма, руб | G4: Подтв. документ | H4: Норматив/основание | I4: Формула/расчет количества | J4: Комментарий
A5: 1 | B5: Гранитный блок/сырье месторождения "Delikato light" (подбор по оттенку/зернистости, мин. жилы/микротрещины) | C5: м³ | D5: =Геометрия!$F$8 | E5: =Вводные_данные!$E$9 | F5: =D5*E5 | G5: КП/счет поставщика | H5: ТЗ; расчет объема сырья | I5: V_партии = V_net×k_allow×k_reject×k_reserve | J5: Коэф. отбора/брака учитывает отбор и повышенный брак.
A6: 2 | B6: Алмазные диски/канат (износ на распиловку) | C6: компл | D6: =1 | E6: 10000 | F6: =D6*E6 | G6: КП поставщика | H6: внутр. норма износа | I6: 1 компл на партию (учет повыш. износа) | J6: Включено как амортизируемый расход на инструмент.
A7: 3 | B7: Алмазные фрезы/профильные головки (износ) | C7: компл | D7: =1 | E7: 8000 | F7: =D7*E7 | G7: КП поставщика | H7: внутр. норма износа | I7: 1 компл на партию | J7: Износ инструмента при фрезеровке/профилировании.
A8: 4 | B8: Бучардировочные головы (пневмо), расход | C8: шт | D8: =ROUNDUP(Геометрия!$B$9*2,0) | E8: 8500 | F8: =D8*E8 | G8: КП поставщика | H8: ресурс головы | I8: 30 м²/голову, 0.2 м² / 30 = 0 шт | J8: Расход зависит от требуемой фактуры.
A9: 5 | B9: Абразивы/шлифкруги/черепашки для лощения (набор зернистостей) | C9: компл | D9: =Вводные_данные!$B$6 | E9: 6500 | F9: =D9*E9 | G9: КП поставщика | H9: 1 компл на шт | I9: 4 компл на 4 шт | J9: Включая ручную доводку переходов.
A10: 6 | B10: Химия и расходники: СОЖ, чистящие средства, ветошь | C10: компл | D10: =Вводные_данные!$B$6 | E10: 1200 | F10: =D10*E10 | G10: внутр. лимит/смета | H10: лимит на шт | I10: 1 компл/шт | J10: Для мойки/сушки между операциями.
A11: 7 | B11: Защитные материалы для разделения зон отделки (скотч, пленка) | C11: компл | D11: =Вводные_данные!$B$6 | E11: 800 | F11: =D11*E11 | G11: счет | H11: лимит на шт | I11: 1 компл/шт | J11: Защита зон лощения при бучардировании.
A12: 8 | B12: Упаковка: тара, прокладки, амортизаторы, уголки | C12: компл | D12: =Вводные_данные!$B$6 | E12: 18000 | F12: =D12*E12 | G12: КП/смета тары | H12: по чертежу упаковки | I12: 1 короб/шт | J12: Упаковка для транспортировки партии.
A13: 9 | B13: Маркировка/бирки/стрейч/скотч/ремни крепления | C13: компл | D13: =Вводные_данные!$B$6 | E13: 1500 | F13: =D13*E13 | G13: счет | H13: лимит на шт | I13: 1 компл/шт | J13: Маркировка, защита кромок.
A14: 10 | B14: СИЗ по операциям (очки, перчатки, респираторы, беруши) — расход | C14: компл | D14: =Вводные_данные!$B$6 | E14: 600 | F14: =D14*E14 | G14: счет | H14: лимит на шт | I14: 1 компл/шт | J14: Пылевые операции (бучардирование/шлифование).
E16: ИТОГО материалы, руб: | F16: =SUM(F5:F14)

Sheet Операции
A1: РАЗДЕЛ 3 — ТЕХНОЛОГИЧЕСКИЕ ОПЕРАЦИИ (ТРУД И МАШИННОЕ ВРЕМЯ)
A2: Трудозатраты нормированы по операциям. Машинное время включает переналадку и межоперационные простои.
A4: № | B4: Операция | C4: Содержание/примечание | D4: Оборудование | E4: Исполнитель (роль) | F4: Норматив/основание | G4: Установки/перевороты | H4: Чел-час/шт. | I4: Чел-час/партия | J4: Ставка, руб/ч | K4: ФОТ, руб | L4: Страх.взносы, руб | M4: Маш-ч/шт. | N4: Маш-ч/партия | O4: Тариф, руб/маш-ч | P4: Маш.затраты, руб | Q4: Мощн., кВт | R4: кВт·ч/шт. | S4: Энергия, руб | T4: Итого прямые, руб | U4: Комментарий
A5: 1 | B5: Входной контроль сырья | C5: Проверка сопроводительных документов, визуальный осмотр, фиксация дефектов; маркировка партии | D5: Кран-балка (внутрицех.) | E5: Мастер цеха (гранит/мрамор) | F5: ТЗ/внутр. регламент входного контроля | G5: 1 перемещение | H5: 1.5 | I5: =H5*Вводные_данные!$B$6 | J5: =IFERROR(VLOOKUP(E5,Вводные_данные!$A$15:$B$21,2,FALSE),0) | K5: =I5*J5 | L5: =K5*Вводные_данные!$E$25 | M5: 0.3 | N5: =M5*Вводные_данные!$B$6 | O5: =IF(D5="",0,IFERROR(VLOOKUP(D5,Вводные_данные!$D$15:$E$21,2,FALSE),0)) | P5: =N5*O5 | Q5: =IF(D5="",0,IFERROR(VLOOKUP(D5,Вводные_данные!$D$15:$G$21,4,FALSE),0)) | R5: =M5*Q5 | S5: =R5*Вводные_данные!$E$24 | T5: =K5+L5+P5+S5 | U5: Высокая категория: доп. проверка дефектов/текстуры.
A6: 2 | B6: Сортировка по оттенку и зернистости, отбраковка жил/микротрещин | C6: Подбор однородной партии с технологическим запасом; отбраковка по дефектам | E6: Мастер цеха (гранит/мрамор) | F6: ТЗ; требования 1 кат. | G6: — | H6: 2.5 | I6: =H6*Вводные_данные!$B$6 | J6: =IFERROR(VLOOKUP(E6,Вводные_данные!$A$15:$B$21,2,FALSE),0) | K6: =I6*J6 | L6: =K6*Вводные_данные!$E$25 | M6: 0 | N6: =M6*Вводные_данные!$B$6 | O6: =IF(D6="",0,IFERROR(VLOOKUP(D6,Вводные_данные!$D$15:$E$21,2,FALSE),0)) | P6: =N6*O6 | Q6: =IF(D6="",0,IFERROR(VLOOKUP(D6,Вводные_данные!$D$15:$G$21,4,FALSE),0)) | R6: =M6*Q6 | S6: =R6*Вводные_данные!$E$24 | T6: =K6+L6+P6+S6 | U6: Повышенный k_reject подтверждается трудозатратами на сортировку.
A7: 3 | B7: Разработка карты раскроя и маршрутной технологии | C7: Раскладка заготовок, учет припусков/керфа; план перестановок/переворотов | E7: Наладчик станков с ЧПУ | F7: ТК/техрегламент | G7: — | H7: 1.8 | I7: =H7*Вводные_данные!$B$6 | J7: =IFERROR(VLOOKUP(E7,Вводные_данные!$A$15:$B$21,2,FALSE),0) | K7: =I7*J7 | L7: =K7*Вводные_данные!$E$25 | M7: 0 | N7: =M7*Вводные_данные!$B$6 | O7: =IF(D7="",0,IFERROR(VLOOKUP(D7,Вводные_данные!$D$15:$E$21,2,FALSE),0)) | P7: =N7*O7 | Q7: =IF(D7="",0,IFERROR(VLOOKUP(D7,Вводные_данные!$D$15:$G$21,4,FALSE),0)) | R7: =M7*Q7 | S7: =R7*Вводные_данные!$E$24 | T7: =K7+L7+P7+S7 | U7: Оптимизация раскроя по карте партии.
A8: 4 | B8: Перемещение блока/слэба к мостовой пиле, строповка | C8: Строповка, перемещение кран-балкой, установка на стол с опорами | D8: Кран-балка (внутрицех.) | E8: Разнорабочий | F8: ФНП/инструкции по строповке | G8: 2 перемещения | H8: 1.2 | I8: =H8*Вводные_данные!$B$6 | J8: =IFERROR(VLOOKUP(E8,Вводные_данные!$A$15:$B$21,2,FALSE),0) | K8: =I8*J8 | L8: =K8*Вводные_данные!$E$25 | M8: 0.5 | N8: =M8*Вводные_данные!$B$6 | O8: =IF(D8="",0,IFERROR(VLOOKUP(D8,Вводные_данные!$D$15:$E$21,2,FALSE),0)) | P8: =N8*O8 | Q8: =IF(D8="",0,IFERROR(VLOOKUP(D8,Вводные_данные!$D$15:$G$21,4,FALSE),0)) | R8: =M8*Q8 | S8: =R8*Вводные_данные!$E$24 | T8: =K8+L8+P8+S8 | U8: Используются траверсы/проставки для исключения прогиба.
A9: 5 | B9: Распиловка сырья на слэб/заготовки (черновая) | C9: Распил с припуском под дальнейший раскрой; контроль перегрева/сколов | D9: SQC2200 (мостовая пила, алмаз) | E9: Распиловщик камня (Камнерез) | F9: внутр. нормы/хронометраж | G9: 1 установка | H9: 3.2 | I9: =H9*Вводные_данные!$B$6 | J9: =IFERROR(VLOOKUP(E9,Вводные_данные!$A$15:$B$21,2,FALSE),0) | K9: =I9*J9 | L9: =K9*Вводные_данные!$E$25 | M9: 2 | N9: =M9*Вводные_данные!$B$6 | O9: =IF(D9="",0,IFERROR(VLOOKUP(D9,Вводные_данные!$D$15:$E$21,2,FALSE),0)) | P9: =N9*O9 | Q9: =IF(D9="",0,IFERROR(VLOOKUP(D9,Вводные_данные!$D$15:$G$21,4,FALSE),0)) | R9: =M9*Q9 | S9: =R9*Вводные_данные!$E$24 | T9: =K9+L9+P9+S9 | U9: Алмазный инструмент повышенного износа на граните.
A10: 6 | B10: Межоперационный контроль после распила | C10: Контроль трещин/жил, плоскостности слэба, замер толщины, фотофиксация | E10: Мастер цеха (гранит/мрамор) | F10: регламент ОТК | G10: — | H10: 1 | I10: =H10*Вводные_данные!$B$6 | J10: =IFERROR(VLOOKUP(E10,Вводные_данные!$A$15:$B$21,2,FALSE),0) | K10: =I10*J10 | L10: =K10*Вводные_данные!$E$25 | M10: 0 | N10: =M10*Вводные_данные!$B$6 | O10: =IF(D10="",0,IFERROR(VLOOKUP(D10,Вводные_данные!$D$15:$E$21,2,FALSE),0)) | P10: =N10*O10 | Q10: =IF(D10="",0,IFERROR(VLOOKUP(D10,Вводные_данные!$D$15:$G$21,4,FALSE),0)) | R10: =M10*Q10 | S10: =R10*Вводные_данные!$E$24 | T10: =K10+L10+P10+S10 | U10: Отбраковка до дорогостоящей мехобработки.
A11: 7 | B11: Раскрой слэба на заготовки изделий + технологический запас | C11: Раскрой с учетом припусков на калибровку и профилирование; минимизация сколов торцов | D11: SQC2200 (мостовая пила, алмаз) | E11: Распиловщик камня (Камнерез) | F11: внутр. нормы/хронометраж | G11: 1 установка | H11: 2.8 | I11: =H11*Вводные_данные!$B$6 | J11: =IFERROR(VLOOKUP(E11,Вводные_данные!$A$15:$B$21,2,FALSE),0) | K11: =I11*J11 | L11: =K11*Вводные_данные!$E$25 | M11: 1.6 | N11: =M11*Вводные_данные!$B$6 | O11: =IF(D11="",0,IFERROR(VLOOKUP(D11,Вводные_данные!$D$15:$E$21,2,FALSE),0)) | P11: =N11*O11 | Q11: =IF(D11="",0,IFERROR(VLOOKUP(D11,Вводные_данные!$D$15:$G$21,4,FALSE),0)) | R11: =M11*Q11 | S11: =R11*Вводные_данные!$E$24 | T11: =K11+L11+P11+S11 | U11: Длина>5 м требует опор по всей длине.
A12: 8 | B12: Калибровка плоскостей и толщины | C12: Калибровка лицевых плоскостей; обеспечение плоскостности и параллельности | D12: JC-1010 (калибровальный станок) | E12: Распиловщик камня (Камнерез) | F12: внутр. нормы/хронометраж | G12: 2 установки/1 переворот | H12: 4 | I12: =H12*Вводные_данные!$B$6 | J12: =IFERROR(VLOOKUP(E12,Вводные_данные!$A$15:$B$21,2,FALSE),0) | K12: =I12*J12 | L12: =K12*Вводные_данные!$E$25 | M12: 2.4 | N12: =M12*Вводные_данные!$B$6 | O12: =IF(D12="",0,IFERROR(VLOOKUP(D12,Вводные_данные!$D$15:$E$21,2,FALSE),0)) | P12: =N12*O12 | Q12: =IF(D12="",0,IFERROR(VLOOKUP(D12,Вводные_данные!$D$15:$G$21,4,FALSE),0)) | R12: =M12*Q12 | S12: =R12*Вводные_данные!$E$24 | T12: =K12+L12+P12+S12 | U12: Включая перестановки и дополнительный замер длинной детали.
A13: 9 | B13: Контроль толщины/плоскостности после калибровки | C13: Замер толщины по сетке точек, контроль плоскостности линейкой/щупом, протокол | E13: Мастер цеха (гранит/мрамор) | F13: регламент ОТК | G13: — | H13: 1.2 | I13: =H13*Вводные_данные!$B$6 | J13: =IFERROR(VLOOKUP(E13,Вводные_данные!$A$15:$B$21,2,FALSE),0) | K13: =I13*J13 | L13: =K13*Вводные_данные!$E$25 | M13: 0 | N13: =M13*Вводные_данные!$B$6 | O13: =IF(D13="",0,IFERROR(VLOOKUP(D13,Вводные_данные!$D$15:$E$21,2,FALSE),0)) | P13: =N13*O13 | Q13: =IF(D13="",0,IFERROR(VLOOKUP(D13,Вводные_данные!$D$15:$G$21,4,FALSE),0)) | R13: =M13*Q13 | S13: =R13*Вводные_данные!$E$24 | T13: =K13+L13+P13+S13 | U13: Архитектурная 1 кат.: усиленный контроль.
A14: 10 | B14: Настройка/верификация программы ЧПУ | C14: Проверка траектории, ограничений по вылету, тестовый проход; установка нуля | D14: Фрезерный ЧПУ/портал | E14: Наладчик станков с ЧПУ | F14: CAM/внутр. регламент | G14: 1 установка | H14: 1.6 | I14: =H14*Вводные_данные!$B$6 | J14: =IFERROR(VLOOKUP(E14,Вводные_данные!$A$15:$B$21,2,FALSE),0) | K14: =I14*J14 | L14: =K14*Вводные_данные!$E$25 | M14: 0.6 | N14: =M14*Вводные_данные!$B$6 | O14: =IF(D14="",0,IFERROR(VLOOKUP(D14,Вводные_данные!$D$15:$E$21,2,FALSE),0)) | P14: =N14*O14 | Q14: =IF(D14="",0,IFERROR(VLOOKUP(D14,Вводные_данные!$D$15:$G$21,4,FALSE),0)) | R14: =M14*Q14 | S14: =R14*Вводные_данные!$E$24 | T14: =K14+L14+P14+S14 | U14: Снижение риска брака на операции профиля/капельника.
A15: 11 | B15: Черновое формообразование (контур, посадочные плоскости) | C15: Фрезеровка контура и базовых плоскостей; формирование конфигурации изделия | D15: Фрезерный ЧПУ/портал | E15: Распиловщик камня (Камнерез) | F15: внутр. нормы/хронометраж | G15: 1 установка | H15: 3.4 | I15: =H15*Вводные_данные!$B$6 | J15: =IFERROR(VLOOKUP(E15,Вводные_данные!$A$15:$B$21,2,FALSE),0) | K15: =I15*J15 | L15: =K15*Вводные_данные!$E$25 | M15: 2 | N15: =M15*Вводные_данные!$B$6 | O15: =IF(D15="",0,IFERROR(VLOOKUP(D15,Вводные_данные!$D$15:$E$21,2,FALSE),0)) | P15: =N15*O15 | Q15: =IF(D15="",0,IFERROR(VLOOKUP(D15,Вводные_данные!$D$15:$G$21,4,FALSE),0)) | R15: =M15*Q15 | S15: =R15*Вводные_данные!$E$24 | T15: =K15+L15+P15+S15 | U15: Длина 5,15 м — повышенные требования к жесткости зажима.
A16: 12 | B16: Переворот/перестановка изделия на кромкообработку | C16: Переворот кран-балкой, установка на роликовые опоры, защита кромок | D16: Кран-балка (внутрицех.) | E16: Разнорабочий | F16: инструкция строповки | G16: 1 переворот | H16: 1 | I16: =H16*Вводные_данные!$B$6 | J16: =IFERROR(VLOOKUP(E16,Вводные_данные!$A$15:$B$21,2,FALSE),0) | K16: =I16*J16 | L16: =K16*Вводные_данные!$E$25 | M16: 0.4 | N16: =M16*Вводные_данные!$B$6 | O16: =IF(D16="",0,IFERROR(VLOOKUP(D16,Вводные_данные!$D$15:$E$21,2,FALSE),0)) | P16: =N16*O16 | Q16: =IF(D16="",0,IFERROR(VLOOKUP(D16,Вводные_данные!$D$15:$G$21,4,FALSE),0)) | R16: =M16*Q16 | S16: =R16*Вводные_данные!$E$24 | T16: =K16+L16+P16+S16 | U16: Риск сколов — применение мягких строп/прокладок.
A17: 13 | B17: Изготовление профиля (капельник) по длине | C17: Профильная обработка кромки; несколько проходов с контролем радиуса и чистоты | D17: SQC600-4D (профильный/кромкообрабатывающий) | E17: Распиловщик камня (Камнерез) | F17: внутр. нормы/хронометраж | G17: 2 прохода | H17: 3.2 | I17: =H17*Вводные_данные!$B$6 | J17: =IFERROR(VLOOKUP(E17,Вводные_данные!$A$15:$B$21,2,FALSE),0) | K17: =I17*J17 | L17: =K17*Вводные_данные!$E$25 | M17: 1.4 | N17: =M17*Вводные_данные!$B$6 | O17: =IF(D17="",0,IFERROR(VLOOKUP(D17,Вводные_данные!$D$15:$E$21,2,FALSE),0)) | P17: =N17*O17 | Q17: =IF(D17="",0,IFERROR(VLOOKUP(D17,Вводные_данные!$D$15:$G$21,4,FALSE),0)) | R17: =M17*Q17 | S17: =R17*Вводные_данные!$E$24 | T17: =K17+L17+P17+S17 | U17: Критическая операция: высокая вероятность брака на длине >5 м.
A18: 14 | B18: Ручная доводка профиля и переходов | C18: Шаблоны/калибры, ручная шлифовка переходов, снятие рисок | E18: Распиловщик камня (Камнерез) | F18: хронометраж/норма | G18: — | H18: 4 | I18: =H18*Вводные_данные!$B$6 | J18: =IFERROR(VLOOKUP(E18,Вводные_данные!$A$15:$B$21,2,FALSE),0) | K18: =I18*J18 | L18: =K18*Вводные_данные!$E$25 | M18: 0 | N18: =M18*Вводные_данные!$B$6 | O18: =IF(D18="",0,IFERROR(VLOOKUP(D18,Вводные_данные!$D$15:$E$21,2,FALSE),0)) | P18: =N18*O18 | Q18: =IF(D18="",0,IFERROR(VLOOKUP(D18,Вводные_данные!$D$15:$G$21,4,FALSE),0)) | R18: =M18*Q18 | S18: =R18*Вводные_данные!$E$24 | T18: =K18+L18+P18+S18 | U18: Усиление стоимости за счет ручной доводки 1 категории.
A19: 15 | B19: Зачистка после калибровки/профиля, устранение микросколов | C19: Локальная шлифовка, подклейка/ремонт при необходимости, доведение кромок | E19: Распиловщик камня (Камнерез) | F19: хронометраж/норма | G19: — | H19: 3 | I19: =H19*Вводные_данные!$B$6 | J19: =IFERROR(VLOOKUP(E19,Вводные_данные!$A$15:$B$21,2,FALSE),0) | K19: =I19*J19 | L19: =K19*Вводные_данные!$E$25 | M19: 0 | N19: =M19*Вводные_данные!$B$6 | O19: =IF(D19="",0,IFERROR(VLOOKUP(D19,Вводные_данные!$D$15:$E$21,2,FALSE),0)) | P19: =N19*O19 | Q19: =IF(D19="",0,IFERROR(VLOOKUP(D19,Вводные_данные!$D$15:$G$21,4,FALSE),0)) | R19: =M19*Q19 | S19: =R19*Вводные_данные!$E$24 | T19: =K19+L19+P19+S19 | U19: Контроль микросколов при перемещениях.
A20: 20 | B20: Подготовка к лощению (абразивы, настройка) | C20: Подбор зернистостей, смена кругов/черепашек, технологическая мойка | E20: Распиловщик камня (Камнерез) | F20: техрегламент | G20: — | H20: 1 | I20: =H20*Вводные_данные!$B$6 | J20: =IFERROR(VLOOKUP(E20,Вводные_данные!$A$15:$B$21,2,FALSE),0) | K20: =I20*J20 | L20: =K20*Вводные_данные!$E$25 | M20: 0 | N20: =M20*Вводные_данные!$B$6 | O20: =IF(D20="",0,IFERROR(VLOOKUP(D20,Вводные_данные!$D$15:$E$21,2,FALSE),0)) | P20: =N20*O20 | Q20: =IF(D20="",0,IFERROR(VLOOKUP(D20,Вводные_данные!$D$15:$G$21,4,FALSE),0)) | R20: =M20*Q20 | S20: =R20*Вводные_данные!$E$24 | T20: =K20+L20+P20+S20 | U20: Межоперационная подготовка.
A21: 21 | B21: Лощение лицевых поверхностей | C21: Лощение вертикальных граней и участков по проекту; контроль равномерности блеска/матовости | D21: ZLMS 2600 / SPG1200-12 (лощильная линия) | E21: Распиловщик камня (Камнерез) | F21: внутр. нормы/хронометраж | G21: 1 установка | H21: 4 | I21: =H21*Вводные_данные!$B$6 | J21: =IFERROR(VLOOKUP(E21,Вводные_данные!$A$15:$B$21,2,FALSE),0) | K21: =I21*J21 | L21: =K21*Вводные_данные!$E$25 | M21: 2.5 | N21: =M21*Вводные_данные!$B$6 | O21: =IF(D21="",0,IFERROR(VLOOKUP(D21,Вводные_данные!$D$15:$E$21,2,FALSE),0)) | P21: =N21*O21 | Q21: =IF(D21="",0,IFERROR(VLOOKUP(D21,Вводные_данные!$D$15:$G$21,4,FALSE),0)) | R21: =M21*Q21 | S21: =R21*Вводные_данные!$E$24 | T21: =K21+L21+P21+S21 | U21: Дополнительная правка по зоне контакта.
A22: 22 | B22: Ручная шлифовка переходов после лощения | C22: Обработка углов/торцов, выведение переходов отделок, устранение «ступенек» | E22: Распиловщик камня (Камнерез) | F22: хронометраж/норма | G22: — | H22: 2.5 | I22: =H22*Вводные_данные!$B$6 | J22: =IFERROR(VLOOKUP(E22,Вводные_данные!$A$15:$B$21,2,FALSE),0) | K22: =I22*J22 | L22: =K22*Вводные_данные!$E$25 | M22: 0 | N22: =M22*Вводные_данные!$B$6 | O22: =IF(D22="",0,IFERROR(VLOOKUP(D22,Вводные_данные!$D$15:$E$21,2,FALSE),0)) | P22: =N22*O22 | Q22: =IF(D22="",0,IFERROR(VLOOKUP(D22,Вводные_данные!$D$15:$G$21,4,FALSE),0)) | R22: =M22*Q22 | S22: =R22*Вводные_данные!$E$24 | T22: =K22+L22+P22+S22 | U22: Архитектурная 1 кат.: повышенная требовательность.
A23: 23 | B23: Мойка, сушка, консервация к отгрузке | C23: Промывка, сушка, защита поверхности от загрязнений и высолов при перевозке | E23: Распиловщик камня (Камнерез) | F23: техрегламент | G23: — | H23: 1 | I23: =H23*Вводные_данные!$B$6 | J23: =IFERROR(VLOOKUP(E23,Вводные_данные!$A$15:$B$21,2,FALSE),0) | K23: =I23*J23 | L23: =K23*Вводные_данные!$E$25 | M23: 0 | N23: =M23*Вводные_данные!$B$6 | O23: =IF(D23="",0,IFERROR(VLOOKUP(D23,Вводные_данные!$D$15:$E$21,2,FALSE),0)) | P23: =N23*O23 | Q23: =IF(D23="",0,IFERROR(VLOOKUP(D23,Вводные_данные!$D$15:$G$21,4,FALSE),0)) | R23: =M23*Q23 | S23: =R23*Вводные_данные!$E$24 | T23: =K23+L23+P23+S23 | U23: Используются чистящие средства/ветошь (см. материалы).
A24: 24 | B24: Контроль геометрии и профиля (промежуточный/финальный) | C24: Контроль длины, прямолинейности, плоскостности, радиуса по шаблону; оформление протокола | E24: Мастер цеха (гранит/мрамор) | F24: регламент ОТК | G24: — | H24: 2 | I24: =H24*Вводные_данные!$B$6 | J24: =IFERROR(VLOOKUP(E24,Вводные_данные!$A$15:$B$21,2,FALSE),0) | K24: =I24*J24 | L24: =K24*Вводные_данные!$E$25 | M24: 0 | N24: =M24*Вводные_данные!$B$6 | O24: =IF(D24="",0,IFERROR(VLOOKUP(D24,Вводные_данные!$D$15:$E$21,2,FALSE),0)) | P24: =N24*O24 | Q24: =IF(D24="",0,IFERROR(VLOOKUP(D24,Вводные_данные!$D$15:$G$21,4,FALSE),0)) | R24: =M24*Q24 | S24: =R24*Вводные_данные!$E$24 | T24: =K24+L24+P24+S24 | U24: Учитывает замеры по сетке точек на длине изделия.
A25: 25 | B25: Комплектация партии и визуальный подбор | C25: Сравнение оттенка/зернистости в партии, маркировка последовательности монтажа | E25: Мастер цеха (гранит/мрамор) | F25: ТЗ | G25: — | H25: 1 | I25: =H25*Вводные_данные!$B$6 | J25: =IFERROR(VLOOKUP(E25,Вводные_данные!$A$15:$B$21,2,FALSE),0) | K25: =I25*J25 | L25: =K25*Вводные_данные!$E$25 | M25: 0 | N25: =M25*Вводные_данные!$B$6 | O25: =IF(D25="",0,IFERROR(VLOOKUP(D25,Вводные_данные!$D$15:$E$21,2,FALSE),0)) | P25: =N25*O25 | Q25: =IF(D25="",0,IFERROR(VLOOKUP(D25,Вводные_данные!$D$15:$G$21,4,FALSE),0)) | R25: =M25*Q25 | S25: =R25*Вводные_данные!$E$24 | T25: =K25+L25+P25+S25 | U25: Отдельная операция, подтверждающая требования к подбору.
A26: 26 | B26: Изготовление тары для партии изделий | C26: Изготовление/сборка коробов, распорки, амортизаторы, упоры | E26: Разнорабочий | F26: чертеж тары/норма | G26: — | H26: 4.5 | I26: =H26*Вводные_данные!$B$6 | J26: =IFERROR(VLOOKUP(E26,Вводные_данные!$A$15:$B$21,2,FALSE),0) | K26: =I26*J26 | L26: =K26*Вводные_данные!$E$25 | M26: 0 | N26: =M26*Вводные_данные!$B$6 | O26: =IF(D26="",0,IFERROR(VLOOKUP(D26,Вводные_данные!$D$15:$E$21,2,FALSE),0)) | P26: =N26*O26 | Q26: =IF(D26="",0,IFERROR(VLOOKUP(D26,Вводные_данные!$D$15:$G$21,4,FALSE),0)) | R26: =M26*Q26 | S26: =R26*Вводные_данные!$E$24 | T26: =K26+L26+P26+S26 | U26: Тара усиливается под массу изделия.
A27: 27 | B27: Упаковка изделия, фиксация в коробе, маркировка | C27: Укладка на прокладки, фиксация, защита кромок, маркировка, фотофиксация | D27: Кран-балка (внутрицех.) | E27: Разнорабочий | F27: регламент упаковки | G27: 1 перемещение | H27: 3 | I27: =H27*Вводные_данные!$B$6 | J27: =IFERROR(VLOOKUP(E27,Вводные_данные!$A$15:$B$21,2,FALSE),0) | K27: =I27*J27 | L27: =K27*Вводные_данные!$E$25 | M27: 0.6 | N27: =M27*Вводные_данные!$B$6 | O27: =IF(D27="",0,IFERROR(VLOOKUP(D27,Вводные_данные!$D$15:$E$21,2,FALSE),0)) | P27: =N27*O27 | Q27: =IF(D27="",0,IFERROR(VLOOKUP(D27,Вводные_данные!$D$15:$G$21,4,FALSE),0)) | R27: =M27*Q27 | S27: =R27*Вводные_данные!$E$24 | T27: =K27+L27+P27+S27 | U27: Включая крановые операции для укладки в короб.
A28: 28 | B28: Погрузка на транспорт и крепление | C28: Погрузка краном, крепление ремнями, проверка устойчивости в кузове | D28: Кран-балка (внутрицех.) | E28: Разнорабочий | F28: инструкция погрузки | G28: 2 перемещения | H28: 1.8 | I28: =H28*Вводные_данные!$B$6 | J28: =IFERROR(VLOOKUP(E28,Вводные_данные!$A$15:$B$21,2,FALSE),0) | K28: =I28*J28 | L28: =K28*Вводные_данные!$E$25 | M28: 0.6 | N28: =M28*Вводные_данные!$B$6 | O28: =IF(D28="",0,IFERROR(VLOOKUP(D28,Вводные_данные!$D$15:$E$21,2,FALSE),0)) | P28: =N28*O28 | Q28: =IF(D28="",0,IFERROR(VLOOKUP(D28,Вводные_данные!$D$15:$G$21,4,FALSE),0)) | R28: =M28*Q28 | S28: =R28*Вводные_данные!$E$24 | T28: =K28+L28+P28+S28 | U28: Фиксация от изгиба/перекоса при погрузке.
B30: ИТОГО по операциям | G30: — | H30: =SUM(H5:H28) | I30: =SUM(I5:I28) | J30: — | K30: =SUM(K5:K28) | L30: =SUM(L5:L28) | N30: =SUM(N5:N28) | P30: =SUM(P5:P28) | S30: =SUM(S5:S28) | T30: =SUM(T5:T28)

Sheet Накладные_и_прибыль
A1: НАКЛАДНЫЕ РАСХОДЫ, РЕЗЕРВЫ И ПРИБЫЛЬ
A2: База начисления раскрыта формулами. Проценты — во вводных данных.
A4: Показатель | B4: Значение | C4: Формула/комментарий
A5: Материалы, руб | B5: =Материалы!$F$16 | C5: Раздел 1
A6: Прямые затраты по операциям, руб | B6: =Операции!$T$30 | C6: ФОТ + взносы + машины + энергия
A7: База накладных (ФОТ+страх.взносы), руб | B7: =Операции!$K$30+Операции!$L$30 | C7: Принята база начисления
A8: Накладные расходы, руб | B8: =B7*Вводные_данные!$E$27 | C8: Накладные = база × %
A9: Промежуточная себестоимость, руб | B9: =B5+B6+B8 | C9: Материалы + операции + накладные
A10: Резерв на технологические риски/брак, руб | B10: =B9*Вводные_данные!$E$29 | C10: Длина>5 м, профиль R25, двойная отделка
A11: Себестоимость с резервом, руб | B11: =B9+B10
A12: Прибыль, руб | B12: =B11*Вводные_данные!$E$28 | C12: Прибыль = себестоимость × %
A13: ИТОГО (себестоимость+прибыль), руб | B13: =B11+B12 | C13: Без учета логистики

Sheet Транспорт
A1: РАЗДЕЛ 2 — ЛОГИСТИКА
A2: Расчет: расстояние × ставка × рейсы + погрузка/разгрузка + страхование груза.
A4: Параметр | B4: Значение | C4: Примечание/источник/документ
A5: Расстояние, км | B5: 940 | C5: дорожное расстояние
A6: Кол-во рейсов | B6: 1 | C6: автомобиль для перевозки партии
A7: Тариф, руб/км (выделенный транспорт) | B7: 120 | C7: редактируемый параметр
A8: Погрузка (кран/манипулятор), руб | B8: 25000 | C8: кран, стропальщики, время
A9: Разгрузка (кран/манипулятор), руб | B9: 35000 | C9: работа с такелажем
A10: Страхование/ответственность перевозчика, % от стоимости | B10: 0.005 | C10: страховой тариф
A12: Перевозка (расстояние×тариф×рейсы), руб | B12: =B5*B7*B6 | C12: Расстояние × руб/км × рейсы
A13: Погрузка, руб | B13: =B8
A14: Разгрузка, руб | B14: =B9
A15: Страхование, руб | B15: =Накладные_и_прибыль!$B$13*B10 | C15: База: (себестоимость+прибыль) × %
A16: ИТОГО логистика, руб | B16: =SUM(B12:B15) | C16: Сумма раздела 2

Sheet ИТОГО
A1: ИТОГОВАЯ СТОИМОСТЬ
A2: ="Стоимость за 1 шт. и за партию "&TEXT(Вводные_данные!$B$6,"0")&" шт., с учетом НДС (ставка во вводных данных)."
A4: Показатель | B4: Значение, руб | C4: Формула/источник
A5: Материалы (раздел 1) | B5: =Накладные_и_прибыль!$B$5
A6: Прямые затраты по операциям (раздел 3) | B6: =Накладные_и_прибыль!$B$6
A7: Накладные расходы | B7: =Накладные_и_прибыль!$B$7
A8: Резерв на риски/брак | B8: =Накладные_и_прибыль!$B$10
A9: Прибыль | B9: =Накладные_и_прибыль!$B$12
A10: ИТОГО производственная часть (без логистики) | B10: =Накладные_и_прибыль!$B$13
A11: Логистика (раздел 2) | B11: =Транспорт!$B$16
A12: ИТОГО без НДС | B12: =B10+B11
A13: НДС | B13: =B12*Вводные_данные!$E$26
A14: ИТОГО с НДС | B14: =B12+B13
A15: Стоимость 1 шт. без НДС | B15: =IF(Вводные_данные!$B$6=0,"-",B12/Вводные_данные!$B$6)
A16: Стоимость 1 шт. с НДС | B16: =IF(Вводные_данные!$B$6=0,"-",B14/Вводные_данные!$B$6)
A17: =IF(Вводные_данные!$E$23="","Стоимость 1 м² без НДС","Стоимость 1 м² ("&Вводные_данные!$E$23&") без НДС") | B17: =IF(Вводные_данные!$B$23*Вводные_данные!$B$6=0,"-",B12/(Вводные_данные!$B$23*Вводные_данные!$B$6)) | C17: Вводные_данные!B23 (база м²/1шт) × кол-во; методика: Вводные_данные!E23
A18: =IF(Вводные_данные!$E$23="","Стоимость 1 м² с НДС","Стоимость 1 м² ("&Вводные_данные!$E$23&") с НДС") | B18: =IF(Вводные_данные!$B$23*Вводные_данные!$B$6=0,"-",B14/(Вводные_данные!$B$23*Вводные_данные!$B$6)) | C18: Вводные_данные!B23 (база м²/1шт) × кол-во; методика: Вводные_данные!E23
A19: =IF(Вводные_данные!$H$23="","Стоимость 1 м.п. без НДС","Стоимость 1 м.п. ("&Вводные_данные!$H$23&") без НДС") | B19: =IF(Вводные_данные!$B$24*Вводные_данные!$B$6=0,"-",B12/(Вводные_данные!$B$24*Вводные_данные!$B$6)) | C19: Вводные_данные!B24 (база м.п./1шт) × кол-во; методика: Вводные_данные!H23
A20: =IF(Вводные_данные!$H$23="","Стоимость 1 м.п. с НДС","Стоимость 1 м.п. ("&Вводные_данные!$H$23&") с НДС") | B20: =IF(Вводные_данные!$B$24*Вводные_данные!$B$6=0,"-",B14/(Вводные_данные!$B$24*Вводные_данные!$B$6)) | C20: Вводные_данные!B24 (база м.п./1шт) × кол-во; методика: Вводные_данные!H23

Sheet Справочники
A1: СПРАВОЧНИКИ И ВЫПАДАЮЩИЕ СПИСКИ
A3: Методика м² | B3: Методика м.п. | C3: Фактура | D3: Сложность
A4: верхняя плоскость (L×W) | B4: по длине L | C4: лощение | D4: простая прямоугольная
A5: лицевая грань (L×T) | B5: длина профиля (L+2W) | C5: бучардирование+лощение | D5: фигурная с радиусами
A6: полная площадь всех граней | B6: периметр (все ребра) | C6: рельефная матовая | D6: сегментная радиусная
A7: площадь бучардирования | C7: полировка | D7: объёмная с профилем
